conduce/__init__.py
conduce/conduce.py
conduce-1.1.5.dist-info/LICENSE
conduce-1.1.5.dist-info/METADATA
conduce-1.1.5.dist-info/WHEEL
conduce-1.1.5.dist-info/top_level.txt
conduce-1.1.5.dist-info/RECORD
