Metadata-Version: 2.1
Name: conduce
Version: 1.1.5
Summary: A config util package to flatten-reduce long keys
Home-page: https://github.com/selphaware/conduce
Author: Usman Ahmad
Author-email: uahmad3013@outlook.com
License: UNKNOWN
Project-URL: Bug Tracker, https://github.com/selphaware/conduce/issues
Platform: UNKNOWN
Classifier: Programming Language :: Python :: 3
Classifier: License :: OSI Approved :: MIT License
Classifier: Operating System :: OS Independent
Requires-Python: >=3.6
License-File: LICENSE
Requires-Dist: PyYAML (==5.4.1)
